setup.cfg
setup.py
lambdascript/__init__.py
lambdascript.egg-info/PKG-INFO
lambdascript.egg-info/SOURCES.txt
lambdascript.egg-info/dependency_links.txt
lambdascript.egg-info/top_level.txt