Metadata-Version: 1.0
Name: lambdascript
Version: 0.1.1.alpha
Summary: A new pure functional language built on the top of Python3.
Home-page: https://github.com/baruchel/lambdascript
Author: Thomas Baruchel
Author-email: baruchel@gmx.com
License: MIT
Platform: UNKNOWN
